PyQt6Ads/_ads.pyd
PyQt6Ads/_ads.pyi
PyQt6/bindings/_ads/AutoHideDockContainer.sip
PyQt6/bindings/_ads/AutoHideSideBar.sip
PyQt6/bindings/_ads/AutoHideTab.sip
PyQt6/bindings/_ads/DockAreaTabBar.sip
PyQt6/bindings/_ads/DockAreaTitleBar.sip
PyQt6/bindings/_ads/DockAreaTitleBar_p.sip
PyQt6/bindings/_ads/DockAreaWidget.sip
PyQt6/bindings/_ads/DockComponentsFactory.sip
PyQt6/bindings/_ads/DockContainerWidget.sip
PyQt6/bindings/_ads/DockFocusController.sip
PyQt6/bindings/_ads/DockManager.sip
PyQt6/bindings/_ads/DockOverlay.sip
PyQt6/bindings/_ads/DockSplitter.sip
PyQt6/bindings/_ads/DockWidget.sip
PyQt6/bindings/_ads/DockWidgetTab.sip
PyQt6/bindings/_ads/DockingStateReader.sip
PyQt6/bindings/_ads/ElidingLabel.sip
PyQt6/bindings/_ads/FloatingDockContainer.sip
PyQt6/bindings/_ads/FloatingDragPreview.sip
PyQt6/bindings/_ads/IconProvider.sip
PyQt6/bindings/_ads/PushButton.sip
PyQt6/bindings/_ads/PyQt6Ads.sip
PyQt6/bindings/_ads/ResizeHandle.sip
PyQt6/bindings/_ads/_ads.toml
PyQt6/bindings/_ads/ads_globals.sip
pyqt6ads-4.4.0.post2.dist-info/WHEEL
pyqt6ads-4.4.0.post2.dist-info/METADATA
pyqt6ads-4.4.0.post2.dist-info/RECORD
