Metadata-Version: 2.1
Name: PyQt6Ads
Version: 4.4.0.post2
Requires-Python: >=3.9
Summary: Python bindings for Qt Advanced Docking System
License: LGPL v2.1
Requires-Dist: PyQt6-sip (>=13.8, <14)
Requires-Dist: PyQt6>=6.5.3,!=6.6
Classifier: Development Status :: 5 - Production/Stable
Classifier: Intended Audience :: Developers
Classifier: License :: OSI Approved :: GNU Lesser General Public License v2 or later (LGPLv2+)
Classifier: Operating System :: MacOS
Classifier: Operating System :: Microsoft :: Windows
Classifier: Operating System :: POSIX :: Linux
Classifier: Programming Language :: Python :: 3
Classifier: Topic :: Software Development :: Libraries :: Python Modules
Classifier: Topic :: Software Development :: Widget Sets
Classifier: Environment :: X11 Applications :: Qt
Classifier: Typing :: Typed
Project-Url: Upstream, https://github.com/githubuser0xFFFF/Qt-Advanced-Docking-System/
Project-Url: Homepage, https://github.com/pyapp-kit/PyQt6Ads
